PSF_Py/__init__.py
PSF_Py/_optimum_k.py
PSF_Py/_optimum_w.py
PSF_Py/_other_functions.py
PSF_Py/_psf_predict.py
PSF_Py/dpsf.py
PSF_Py/plot.py
PSF_Py/psf.py
PSF_Py/ts.py
PSF_Py-0.3.dist-info/LICENSE
PSF_Py-0.3.dist-info/METADATA
PSF_Py-0.3.dist-info/WHEEL
PSF_Py-0.3.dist-info/top_level.txt
PSF_Py-0.3.dist-info/RECORD
