Metadata-Version: 2.1
Name: PSF-Py
Version: 0.3
Summary: PSF: Pattern Sequence-based Forecasting (PSF) algorithm
Home-page: https://github.com/pypa/sampleproject
Author: Mayur Shende, Neeraj Bokde
Author-email: mayur.k.shende@gmail.com, neerajdhanraj@gmail.com
Project-URL: Bug Tracker, https://github.com/Mayur1009/PSF_Py/issues
Classifier: Programming Language :: Python :: 3
Classifier: License :: OSI Approved :: MIT License
Classifier: Operating System :: OS Independent
License-File: LICENSE
Requires-Dist: pandas
Requires-Dist: numpy
Requires-Dist: scikit-learn
Requires-Dist: matplotlib
